airia/__init__.py
airia/constants.py
airia/exceptions.py
airia/logs.py
airia/client/__init__.py
airia/client/async_client.py
airia/client/base_client.py
airia/client/sync_client.py
airia/client/_request_handler/__init__.py
airia/client/_request_handler/async_request_handler.py
airia/client/_request_handler/base_request_handler.py
airia/client/_request_handler/sync_request_handler.py
airia/client/attachments/__init__.py
airia/client/attachments/async_attachments.py
airia/client/attachments/base_attachments.py
airia/client/attachments/sync_attachments.py
airia/client/conversations/__init__.py
airia/client/conversations/async_conversations.py
airia/client/conversations/base_conversations.py
airia/client/conversations/sync_conversations.py
airia/client/data_vector_search/__init__.py
airia/client/data_vector_search/async_data_vector_search.py
airia/client/data_vector_search/base_data_vector_search.py
airia/client/data_vector_search/sync_data_vector_search.py
airia/client/deployments/__init__.py
airia/client/deployments/async_deployments.py
airia/client/deployments/base_deployments.py
airia/client/deployments/sync_deployments.py
airia/client/library/__init__.py
airia/client/library/async_library.py
airia/client/library/base_library.py
airia/client/library/sync_library.py
airia/client/models/__init__.py
airia/client/models/async_models.py
airia/client/models/base_models.py
airia/client/models/sync_models.py
airia/client/pipeline_execution/__init__.py
airia/client/pipeline_execution/async_pipeline_execution.py
airia/client/pipeline_execution/base_pipeline_execution.py
airia/client/pipeline_execution/sync_pipeline_execution.py
airia/client/pipeline_import/__init__.py
airia/client/pipeline_import/async_pipeline_import.py
airia/client/pipeline_import/base_pipeline_import.py
airia/client/pipeline_import/sync_pipeline_import.py
airia/client/pipelines_config/__init__.py
airia/client/pipelines_config/async_pipelines_config.py
airia/client/pipelines_config/base_pipelines_config.py
airia-0.1.35.dist-info/licenses/LICENSE
airia-0.1.35.dist-info/METADATA
airia-0.1.35.dist-info/WHEEL
airia-0.1.35.dist-info/top_level.txt
airia-0.1.35.dist-info/RECORD
