Metadata-Version: 2.4
Name: airia
Version: 0.1.35
Summary: Python SDK for Airia API
Author-email: Airia LLC <support@airia.com>
License: MIT
Classifier: Programming Language :: Python :: 3
Classifier: Programming Language :: Python :: 3.9
Classifier: Programming Language :: Python :: 3.10
Classifier: Programming Language :: Python :: 3.11
Classifier: Programming Language :: Python :: 3.12
Classifier: Programming Language :: Python :: 3.13
Classifier: License :: OSI Approved :: MIT License
Classifier: Operating System :: OS Independent
Requires-Python: >=3.9
License-File: LICENSE
Requires-Dist: requests>=2.32.3
Requires-Dist: aiohttp>=3.13.3
Requires-Dist: pydantic>=2.11.0
Provides-Extra: anthropic
Requires-Dist: anthropic>=0.49.0; extra == "anthropic"
Provides-Extra: openai
Requires-Dist: openai>=1.74.0; extra == "openai"
Provides-Extra: all
Requires-Dist: anthropic>=0.49.0; extra == "all"
Requires-Dist: openai>=1.74.0; extra == "all"
Dynamic: license-file
